content_security_policy/__init__.py
content_security_policy/base_classes.py
content_security_policy/constants.py
content_security_policy/directives.py
content_security_policy/django/auto_src/__init__.py
content_security_policy/django/auto_src/base.py
content_security_policy/django/build_settings.py
content_security_policy/django/constants.py
content_security_policy/django/exceptions.py
content_security_policy/django/manage.py
content_security_policy/django/management/commands/buildcsp.py
content_security_policy/django/middleware.py
content_security_policy/django/settings.py
content_security_policy/django/static/README.md
content_security_policy/django/static/main.js
content_security_policy/django/static/some-lib.js
content_security_policy/django/test/test_buildcsp.py
content_security_policy/django/test/test_middleware.py
content_security_policy/django/test/test_watch_dir/README.md
content_security_policy/django/test/test_watch_dir/bundle.js
content_security_policy/django/test/test_watch_dir/index.js
content_security_policy/django/urls.py
content_security_policy/django/utils/__init__.py
content_security_policy/django/utils/settings.py
content_security_policy/django/views.py
content_security_policy/django/wsgi.py
content_security_policy/exceptions.py
content_security_policy/parse.py
content_security_policy/patterns.py
content_security_policy/py.typed
content_security_policy/test/__init__.py
content_security_policy/test/test_directives.py
content_security_policy/test/test_equality.py
content_security_policy/test/test_examples.py
content_security_policy/test/test_parsing.py
content_security_policy/test/test_policy.py
content_security_policy/test/test_source_list_directives.py
content_security_policy/test/test_values.py
content_security_policy/utils.py
content_security_policy/values.py
content_security_policy-0.2.3.dist-info/LICENSE
content_security_policy-0.2.3.dist-info/METADATA
content_security_policy-0.2.3.dist-info/WHEEL
content_security_policy-0.2.3.dist-info/RECORD
