Metadata-Version: 2.1
Name: content-security-policy
Version: 0.2.3
Summary: Create, maintain, parse and manipulate Content Security Policies
Author: no.shoes
Author-email: no.shoes@posteo.net
Requires-Python: >=3.10,<4.0
Classifier: Programming Language :: Python :: 3
Classifier: Programming Language :: Python :: 3.10
Classifier: Programming Language :: Python :: 3.11
Classifier: Programming Language :: Python :: 3.12
Provides-Extra: django
Requires-Dist: watchdog (>=3.0.0,<4.0.0) ; extra == "django"
